csspin_python/behave.py
csspin_python/behave_schema.yaml
csspin_python/debugpy.py
csspin_python/debugpy_schema.yaml
csspin_python/devpi.py
csspin_python/devpi_schema.yaml
csspin_python/playwright.py
csspin_python/playwright_schema.yaml
csspin_python/pytest.py
csspin_python/pytest_schema.yaml
csspin_python/python.py
csspin_python/python_schema.yaml
csspin_python/radon.py
csspin_python/radon_schema.yaml
csspin_python/uv_provisioner.py
csspin_python/uv_provisioner_schema.yaml
csspin_python-3.2.0.dist-info/licenses/LICENSE
csspin_python-3.2.0.dist-info/METADATA
csspin_python-3.2.0.dist-info/WHEEL
csspin_python-3.2.0.dist-info/top_level.txt
csspin_python-3.2.0.dist-info/RECORD
