Metadata-Version: 2.4
Name: csspin-python
Version: 3.2.0
Summary: Plugin-package for csspin providing Python related plugins
Author-email: CONTACT Software GmbH <info@contact-software.com>
Maintainer-email: Waleri Enns <waleri.enns@contact-software.com>, Benjamin Thomas Schwertfeger <benjaminthomas.schwertfeger@contact-software.com>, Fabian Hafer <fabian.hafer@contact-software.com>
License-Expression: Apache-2.0
Project-URL: CONTACT Software GmbH, https://contact-software.com
Project-URL: Documentation, https://csspin-python.readthedocs.io/en/stable/
Project-URL: Issue Tracker, https://github.com/cslab/csspin-python/issues
Project-URL: Release Notes, https://csspin-python.readthedocs.io/en/stable/relnotes.html
Project-URL: Repository, https://github.com/cslab/csspin-python
Classifier: Environment :: Console
Classifier: Development Status :: 5 - Production/Stable
Classifier: Intended Audience :: Developers
Classifier: Operating System :: OS Independent
Classifier: Programming Language :: Python :: 3
Classifier: Programming Language :: Python :: 3.9
Classifier: Programming Language :: Python :: 3.10
Classifier: Programming Language :: Python :: 3.11
Classifier: Programming Language :: Python :: 3.12
Classifier: Programming Language :: Python :: 3.13
Classifier: Topic :: Software Development
Requires-Python: >=3.9
License-File: LICENSE
Requires-Dist: platformdirs~=4.3.8
Requires-Dist: virtualenv
Provides-Extra: aws-auth
Requires-Dist: csaccess>=0.1.0; extra == "aws-auth"
Provides-Extra: uv
Requires-Dist: tomli; python_version < "3.11" and extra == "uv"
Requires-Dist: tomli-w; extra == "uv"
Requires-Dist: uv; extra == "uv"
Dynamic: license-file
